odoo8_addon_account_invoice_import_zugferd-8.0.1.0.0.99.dev8-nspkg.pth
odoo_addons/account_invoice_import_zugferd/README.rst
odoo_addons/account_invoice_import_zugferd/__init__.py
odoo_addons/account_invoice_import_zugferd/__openerp__.py
odoo_addons/account_invoice_import_zugferd/demo/demo_data.xml
odoo_addons/account_invoice_import_zugferd/i18n/account_invoice_import_zugferd.pot
odoo_addons/account_invoice_import_zugferd/i18n/fr.po
odoo_addons/account_invoice_import_zugferd/i18n/sl.po
odoo_addons/account_invoice_import_zugferd/static/description/icon.png
odoo_addons/account_invoice_import_zugferd/tests/__init__.py
odoo_addons/account_invoice_import_zugferd/tests/test_zugferd.py
odoo_addons/account_invoice_import_zugferd/tests/files/ZUGFeRD_1p0_BASIC_Einfach.pdf
odoo_addons/account_invoice_import_zugferd/tests/files/ZUGFeRD_1p0_BASIC_Rechnungskorrektur.pdf
odoo_addons/account_invoice_import_zugferd/tests/files/ZUGFeRD_1p0_COMFORT_Einfach.pdf
odoo_addons/account_invoice_import_zugferd/tests/files/ZUGFeRD_1p0_COMFORT_Einfach.pdf-ZUGFeRD-invoice.xml
odoo_addons/account_invoice_import_zugferd/tests/files/ZUGFeRD_1p0_COMFORT_Haftpflichtversicherung_Versicherungssteuer.pdf
odoo_addons/account_invoice_import_zugferd/tests/files/ZUGFeRD_1p0_COMFORT_Kraftfahrversicherung_Bruttopreise.pdf
odoo_addons/account_invoice_import_zugferd/tests/files/ZUGFeRD_1p0_COMFORT_Rabatte.pdf
odoo_addons/account_invoice_import_zugferd/tests/files/ZUGFeRD_1p0_COMFORT_Rechnungskorrektur.pdf
odoo_addons/account_invoice_import_zugferd/tests/files/ZUGFeRD_1p0_COMFORT_SEPA_Prenotification.pdf
odoo_addons/account_invoice_import_zugferd/tests/files/ZUGFeRD_1p0_COMFORT_Sachversicherung_berechneter_Steuersatz.pdf
odoo_addons/account_invoice_import_zugferd/tests/files/ZUGFeRD_1p0_EXTENDED_Kostenrechnung.pdf
odoo_addons/account_invoice_import_zugferd/tests/files/ZUGFeRD_1p0_EXTENDED_Rechnungskorrektur.pdf
odoo_addons/account_invoice_import_zugferd/tests/files/ZUGFeRD_1p0_EXTENDED_Warenrechnung.pdf
odoo8_addon_account_invoice_import_zugferd-8.0.1.0.0.99.dev8.dist-info/METADATA
odoo8_addon_account_invoice_import_zugferd-8.0.1.0.0.99.dev8.dist-info/WHEEL
odoo8_addon_account_invoice_import_zugferd-8.0.1.0.0.99.dev8.dist-info/namespace_packages.txt
odoo8_addon_account_invoice_import_zugferd-8.0.1.0.0.99.dev8.dist-info/top_level.txt
odoo8_addon_account_invoice_import_zugferd-8.0.1.0.0.99.dev8.dist-info/RECORD
